rbool/__init__.py
rbool/base.py
rbool/bool1d.py
rbool/converter.py
rbool/error.py
rbool/limits.py
rbool/numbs.py
rbool/singles.py
rbool/transform.py
rbool-0.0.4.dist-info/LICENSE.md
rbool-0.0.4.dist-info/METADATA
rbool-0.0.4.dist-info/WHEEL
rbool-0.0.4.dist-info/RECORD
